textqrcode/__init__.py
textqrcode/main.py
text_to_qrcode-0.1.dist-info/METADATA
text_to_qrcode-0.1.dist-info/WHEEL
text_to_qrcode-0.1.dist-info/entry_points.txt
text_to_qrcode-0.1.dist-info/top_level.txt
text_to_qrcode-0.1.dist-info/RECORD
