Metadata-Version: 2.1
Name: text_to_qrcode
Version: 0.1
Summary: A package for calculating factorial.
Home-page: https://github.com/Sam-Sisodia/text_to_qQrocde.git
Author: Sajal Sisodia
Author-email: Sajal89304@gmail.com
Classifier: Programming Language :: Python :: 3
Classifier: License :: OSI Approved :: MIT License
Classifier: Operating System :: OS Independent
Requires-Dist: qrcode
